amocarray/__init__.py
amocarray-0.1.1.dist-info/METADATA
amocarray-0.1.1.dist-info/WHEEL
amocarray-0.1.1.dist-info/top_level.txt
amocarray-0.1.1.dist-info/RECORD
