Metadata-Version: 2.4
Name: amocarray
Version: 0.1.1
Summary: [DEPRECATED] Please use AMOCatlas instead
Home-page: https://github.com/eleanorfrajka/amocarray
Author: Eleanor Frajka-Williams
Author-email: eleanorrajka@gmail.com
Keywords: deprecated amoc atlas oceanography
Classifier: Development Status :: 7 - Inactive
Classifier: Intended Audience :: Science/Research
Classifier: License :: OSI Approved :: MIT License
Classifier: Programming Language :: Python :: 3
Classifier: Topic :: Scientific/Engineering
Requires-Python: >=3.7
Requires-Dist: AMOCatlas
Dynamic: author
Dynamic: author-email
Dynamic: classifier
Dynamic: description
Dynamic: description-content-type
Dynamic: home-page
Dynamic: keywords
Dynamic: requires-dist
Dynamic: requires-python
Dynamic: summary
